pyhxexpress/__init__.py
pyhxexpress/config.py
pyhxexpress/hxex.py
pyhxexpress/hxex_fragments.py
pyhxexpress/hxex_mzml_utils.py
pyhxexpress/hxex_utils.py
pyhxexpress-0.1.1.dist-info/licenses/LICENSE.txt
pyhxexpress-0.1.1.dist-info/METADATA
pyhxexpress-0.1.1.dist-info/WHEEL
pyhxexpress-0.1.1.dist-info/top_level.txt
pyhxexpress-0.1.1.dist-info/RECORD
