Metadata-Version: 2.4
Name: pyhxexpress
Version: 0.1.1
Summary: pyHXExpress
Home-page: https://github.com/tuttlelm/pyHXExpress
Author: <Lisa M Tuttle>
Author-email: <tuttlelm@uw.edu>
License: GPLv3
Keywords: HDX-MS
Classifier: Development Status :: 4 - Beta
Classifier: Intended Audience :: Science/Research
Classifier: License :: OSI Approved :: GNU General Public License v3 or later (GPLv3+)
Classifier: Programming Language :: Python :: 3
License-File: LICENSE.txt
Requires-Dist: numpy
Requires-Dist: pandas
Requires-Dist: pymupdf
Requires-Dist: scipy
Requires-Dist: matplotlib
Requires-Dist: pyteomics
Requires-Dist: brain-isotopic-distribution
Requires-Dist: biopython
Dynamic: author
Dynamic: author-email
Dynamic: classifier
Dynamic: description
Dynamic: home-page
Dynamic: keywords
Dynamic: license
Dynamic: license-file
Dynamic: requires-dist
Dynamic: summary
